README.rst
nock.py
setup.py
nock.egg-info/PKG-INFO
nock.egg-info/SOURCES.txt
nock.egg-info/dependency_links.txt
nock.egg-info/entry_points.txt
nock.egg-info/not-zip-safe
nock.egg-info/top_level.txt