Metadata-Version: 1.1
Name: nock
Version: 0.2
Summary: Nock, Nock. Hoon's there?
Home-page: http://github.com/eykd/nock
Author: David Eyk
Author-email: david.eyk@gmail.com
License: BSD
Platform: UNKNOWN
Classifier: Development Status :: 4 - Beta
Classifier: Environment :: Console
Classifier: Intended Audience :: Developers
Classifier: License :: OSI Approved :: BSD License
Classifier: Natural Language :: English
Classifier: Topic :: Software Development :: Libraries
